dataconda/__init__.py
dataconda/dataconda.py
dataconda-0.0.1.dist-info/METADATA
dataconda-0.0.1.dist-info/WHEEL
dataconda-0.0.1.dist-info/top_level.txt
dataconda-0.0.1.dist-info/RECORD
