Metadata-Version: 2.1
Name: dataconda
Version: 0.0.1
Summary: A python library for data
Home-page: https://github.com/ploppy-pigeon/DataConda
Author: Vinayak Vikram
Author-email: subram.sesh@gmail.com
License: UNKNOWN
Platform: UNKNOWN
Classifier: Programming Language :: Python :: 3
Classifier: License :: OSI Approved :: MIT License
Classifier: Operating System :: OS Independent
Requires-Python: >=3.6
